roman_converter/__init__.py
roman_converter/app.py
roman_converter-1.0.dist-info/LICENSE
roman_converter-1.0.dist-info/METADATA
roman_converter-1.0.dist-info/WHEEL
roman_converter-1.0.dist-info/entry_points.txt
roman_converter-1.0.dist-info/top_level.txt
roman_converter-1.0.dist-info/RECORD
